lazytui/__init__.py
lazytui/color.py
lazytui/fmt.py
lazytui/grid.py
lazytui/renderer.py
lazytui/user_defined.py
lazytui-0.0.3.dist-info/METADATA
lazytui-0.0.3.dist-info/WHEEL
lazytui-0.0.3.dist-info/top_level.txt
lazytui-0.0.3.dist-info/RECORD
