Metadata-Version: 2.1
Name: lazytui
Version: 0.0.3
Summary: A terminal UI for the la(z)yperson
Home-page: https://github.com/kylepollina/lazytui
Author: Kyle Pollina
Author-email: kylepollina@pm.me
License: MIT
Platform: UNKNOWN
